Workbook

Sheet Assumptions
A1: CORE ASSUMPTIONS
A2: Current Salary | B2: 72000 | C2: Reference only. Not used in calculations.
A3: Hourly Time Value | B3: 21 | C3: Gross pay rate (£37/hr) less 42% marginal tax/NI = net take-home per hour of work. Real cash spending power.
A4: Combined Tax/NI Rate | B4: 0.42 | C4: Marginal rate at £72k+. 40% income tax + 2% NI on salary above £50,270.
A5: Discount Rate | B5: 0.07 | C5: Time value of money. 7% = equity-like opportunity cost, consistent with Peter's investment approach.
A6: Working Years Remaining | B6: 20 | C6: Born April 1985, age 40. Assumes working until ~age 60. Adjust if planning earlier/later retirement.
A8: PHASES 1-3: CORE SKILL STACK
A9: Annual Salary Uplift (Phases 1-3) | B9: 9000 | C9: Target £6-10k range. £9k = high-midpoint. Reflects Python + SQL + Financial Analysis + Stats + ML combined.
A10: Delay Before Uplift (years) | B10: 2 | C10: Courses complete ~Feb 2027. 12 months to consolidate, demonstrate impact, and secure promotion/move. Benefit from ~Feb 2028.
A11: Benefit Years (Phases 1-3) | B11: =B6-B10 -> 18 | C11: Working years remaining minus delay. Skills compound over full remaining career.
A12: Delayed Annuity Factor (Phases 1-3) | B12: =IF(1<=B11, 1/(1+B5)^(B10+1), 0)+IF(2<=B11, 1/(1+B5)^(B10+2), 0)+IF(3<=B11, 1/(1+B5)^(B10+3), 0)+IF(4<=B11, 1/(1+B5)^(B10+4), 0)+IF(5<=B11, 1/(1+B5)^(B10+5), 0)+IF(6<=B11, 1/(1+B5)^(B10+6), 0)+IF(7<=B11, 1/(1+B5)^(B10+7), 0)+IF(8<=B11, 1/(1+B5)^(B10+8), 0)+IF(9<=B11, 1/(1+B5)^(B10+9), 0)+IF(10<=B11, 1/(1+B5)^(B10+10), 0)+IF(11<=B11, 1/(1+B5)^(B10+11), 0)+IF(12<=B11, 1/(1+B5)^(B10+12), 0)+IF(13<=B11, 1/(1+B5)^(B10+13), 0)+IF(14<=B11, 1/(1+B5)^(B10+14), 0)+IF(15<=B11, 1/(1+B5)^(B10+15), 0)+IF(16<=B11, 1/(1+B5)^(B10+16), 0)+IF(17<=B11, 1/(1+B5)^(B10+17), 0)+IF(18<=B11, 1/(1+B5)^(B10+18), 0)+IF(19<=B11, 1/(1+B5)^(B10+19), 0)+IF(20<=B11, 1/(1+B5)^(B10+20), 0)+IF(21<=B11, 1/(1+B5)^(B10+21), 0)+IF(22<=B11, 1/(1+B5)^(B10+22), 0)+IF(23<=B11, 1/(1+B5)^(B10+23), 0)+IF(24<=B11, 1/(1+B5)^(B10+24), 0)+IF(25<=B11, 1/(1+B5)^(B10+25), 0) -> 8.7859961 | C12: Sum of discount factors from (delay+1) to (delay+benefit_years). Derived from inputs above.
A14: PHASE 4: AI ENGINEER (INCREMENTAL)
A15: Annual Salary Uplift (Phase 4) | B15: 2000 | C15: Incremental uplift ON TOP of Phases 1-3. Raises ceiling from £78-84k to £85-90k range, or accelerates arrival.
A16: Delay Before Uplift (years) | B16: 2.5 | C16: Course complete ~Jul 2027. 12 months to apply. Benefit from ~Jul 2028 = 2.5 years from today.
A17: Benefit Years (Phase 4) | B17: =B6-B16 -> 17.5 | C17: Working years remaining minus Phase 4 delay.
A18: Delayed Annuity Factor (Phase 4) | B18: =IF(1<=B17, 1/(1+B5)^(B16+1), 0)+IF(2<=B17, 1/(1+B5)^(B16+2), 0)+IF(3<=B17, 1/(1+B5)^(B16+3), 0)+IF(4<=B17, 1/(1+B5)^(B16+4), 0)+IF(5<=B17, 1/(1+B5)^(B16+5), 0)+IF(6<=B17, 1/(1+B5)^(B16+6), 0)+IF(7<=B17, 1/(1+B5)^(B16+7), 0)+IF(8<=B17, 1/(1+B5)^(B16+8), 0)+IF(9<=B17, 1/(1+B5)^(B16+9), 0)+IF(10<=B17, 1/(1+B5)^(B16+10), 0)+IF(11<=B17, 1/(1+B5)^(B16+11), 0)+IF(12<=B17, 1/(1+B5)^(B16+12), 0)+IF(13<=B17, 1/(1+B5)^(B16+13), 0)+IF(14<=B17, 1/(1+B5)^(B16+14), 0)+IF(15<=B17, 1/(1+B5)^(B16+15), 0)+IF(16<=B17, 1/(1+B5)^(B16+16), 0)+IF(17<=B17, 1/(1+B5)^(B16+17), 0)+IF(18<=B17, 1/(1+B5)^(B16+18), 0)+IF(19<=B17, 1/(1+B5)^(B16+19), 0)+IF(20<=B17, 1/(1+B5)^(B16+20), 0)+IF(21<=B17, 1/(1+B5)^(B16+21), 0)+IF(22<=B17, 1/(1+B5)^(B16+22), 0)+IF(23<=B17, 1/(1+B5)^(B16+23), 0)+IF(24<=B17, 1/(1+B5)^(B16+24), 0)+IF(25<=B17, 1/(1+B5)^(B16+25), 0) -> 8.2439199 | C18: Sum of discount factors for Phase 4 benefit period.
A20: METHODOLOGY
A21: Each course gets a contribution weight (% of total uplift it enables). Weights sum to 100% within each phase.
A22: Courses are interdependent — Python enables Financial Python enables ML. Weights reflect marginal contribution.
A23: NPV = Gross Uplift × (1 - Tax Rate) × Delayed Annuity Factor.
A24: Net Benefit = NPV - Time Cost. Positive = course pays back more than time invested.
A25: Benefit/Hour = Net Benefit ÷ Hours. Higher = more efficient use of time.
A26: ROI Multiple = NPV ÷ Time Cost. Above 1.0x = positive return.
A27: Phase 4 is INCREMENTAL — it adds to, not dilutes, the Phase 1-3 uplift.
A28: Blue cells = adjustable inputs. Black cells = formulas. Green cells = cross-sheet references.
A29: The model is conservative: it excludes productivity gains, better pricing decisions, personal investment returns, and career optionality.
A31: TIMELINE
A32: Mar 2026 - May 2026 | B32: Phase 1: Python + SQL (47 hours) | C32: 3-4 hrs/week
A33: Jun 2026 - Sep 2026 | B33: Phase 2: Financial Python + Statistics (30 hours) | C33: 3-4 hrs/week
A34: Oct 2026 - Feb 2027 | B34: Phase 3: ML/AI Career Path first 60-70% (35 hours) | C34: 3-4 hrs/week
A35: Feb 2028 | B35: Phases 1-3 salary uplift begins | C35: 12 months after Phase 3 completion
A36: Mar 2027 - Jul 2027 | B36: Phase 4: AI Engineer Career Path (40 hours) | C36: 3-4 hrs/week
A37: Jul 2028 | B37: Phase 4 salary uplift begins | C37: 12 months after Phase 4 completion
A38: ~2046 | B38: Retirement (age ~61) | C38: End of benefit period

Sheet Course Analysis
A1: Tier | B1: Course | C1: Hrs | D1: Phase | E1: Time Cost | F1: Uplift Share | G1: Gross £/yr | H1: NPV (post-tax) | I1: Net Benefit | J1: Benefit/Hr | K1: ROI | L1: Rationale
A2: TIER 1 | B2: Learn Python 3 | C2: 24 | D2: 1 | E2: =C2*Assumptions!B3 -> 504 | F2: 0.25 | G2: =F2*Assumptions!B9 -> 2250 | H2: =G2*(1-Assumptions!B4)*Assumptions!B12 -> 11465.725 | I2: =H2-E2 -> 10961.725 | J2: =IF(C2>0,I2/C2,0) -> 456.73854 | K2: =IF(E2>0,H2/E2,0) -> 22.749454 | L2: Foundation for everything. Enables automation, financial modelling, AI tooling, and Data Fellowship prep.
A3: TIER 1 | B3: Learn SQL | C3: 5 | D3: 1 | E3: =C3*Assumptions!B3 -> 105 | F3: 0.08 | G3: =F3*Assumptions!B9 -> 720 | H3: =G3*(1-Assumptions!B4)*Assumptions!B12 -> 3669.032 | I3: =H3-E3 -> 3564.032 | J3: =IF(C3>0,I3/C3,0) -> 712.80639 | K3: =IF(E3>0,H3/E3,0) -> 34.943162 | L3: Table stakes at senior analytical level. Query pricing databases directly without waiting for data team.
A4: TIER 1 | B4: Analyze Data with SQL (Skill Path) | C4: 18 | D4: 1 | E4: =C4*Assumptions!B3 -> 378 | F4: 0.1 | G4: =F4*Assumptions!B9 -> 900 | H4: =G4*(1-Assumptions!B4)*Assumptions!B12 -> 4586.29 | I4: =H4-E4 -> 4208.29 | J4: =IF(C4>0,I4/C4,0) -> 233.79389 | K4: =IF(E4>0,H4/E4,0) -> 12.133042 | L4: Takes SQL to practical analysis. Joins, aggregates, case studies on Ethernet/Optical pricing data.
A5: TIER 2 | B5: Analyze Financial Data with Python (Skill Path) | C5: 20 | D5: 2 | E5: =C5*Assumptions!B3 -> 420 | F5: 0.2 | G5: =F5*Assumptions!B9 -> 1800 | H5: =G5*(1-Assumptions!B4)*Assumptions!B12 -> 9172.5799 | I5: =H5-E5 -> 8752.5799 | J5: =IF(C5>0,I5/C5,0) -> 437.629 | K5: =IF(E5>0,H5/E5,0) -> 21.839476 | L5: Pandas, NumPy, Matplotlib, regression, portfolio optimisation. Maps to pricing models and personal investments.
A6: TIER 2 | B6: Learn Statistics with Python | C6: 10 | D6: 2 | E6: =C6*Assumptions!B3 -> 210 | F6: 0.1 | G6: =F6*Assumptions!B9 -> 900 | H6: =G6*(1-Assumptions!B4)*Assumptions!B12 -> 4586.29 | I6: =H6-E6 -> 4376.29 | J6: =IF(C6>0,I6/C6,0) -> 437.629 | K6: =IF(E6>0,H6/E6,0) -> 21.839476 | L6: Distributions, variance, hypothesis testing. Essential foundation before ML content.
A7: TIER 2 | B7: ML/AI Engineer Career Path (first 60-70%) | C7: 35 | D7: 3 | E7: =C7*Assumptions!B3 -> 735 | F7: 0.22 | G7: =F7*Assumptions!B9 -> 1980 | H7: =G7*(1-Assumptions!B4)*Assumptions!B12 -> 10089.838 | I7: =H7-E7 -> 9354.8379 | J7: =IF(C7>0,I7/C7,0) -> 267.28108 | K7: =IF(E7>0,H7/E7,0) -> 13.727671 | L7: Commercial leaders with ML literacy are rare. Strongest differentiator for Head of Pricing / Commercial Director.
A8: TIER 3 | B8: Learn How to Use AI for Data Analysis | C8: 3 | D8: QW | E8: =C8*Assumptions!B3 -> 63 | F8: 0.02 | G8: =F8*Assumptions!B9 -> 180 | H8: =G8*(1-Assumptions!B4)*Assumptions!B12 -> 917.25799 | I8: =H8-E8 -> 854.25799 | J8: =IF(C8>0,I8/C8,0) -> 284.75266 | K8: =IF(E8>0,H8/E8,0) -> 14.559651 | L8: Using LLMs as analytics assistants in Python. Productivity tool, minimal standalone salary impact.
A9: TIER 3 | B9: Web Scraping with Beautiful Soup | C9: 4 | D9: QW | E9: =C9*Assumptions!B3 -> 84 | F9: 0.01 | G9: =F9*Assumptions!B9 -> 90 | H9: =G9*(1-Assumptions!B4)*Assumptions!B12 -> 458.629 | I9: =H9-E9 -> 374.629 | J9: =IF(C9>0,I9/C9,0) -> 93.657249 | K9: =IF(E9>0,H9/E9,0) -> 5.459869 | L9: Pull competitor pricing, Ofcom data programmatically. Niche competitive intelligence.
A10: TIER 3 | B10: AI for FP&A | C10: 1 | D10: QW | E10: =C10*Assumptions!B3 -> 21 | F10: 0.01 | G10: =F10*Assumptions!B9 -> 90 | H10: =G10*(1-Assumptions!B4)*Assumptions!B12 -> 458.629 | I10: =H10-E10 -> 437.629 | J10: =IF(C10>0,I10/C10,0) -> 437.629 | K10: =IF(E10>0,H10/E10,0) -> 21.839476 | L10: Forecasting, scenario modelling, variance analysis with AI. Relevant but too narrow alone.
A11: TIER 3 | B11: SQL for Business Metrics (Intermediate) | C11: 3 | D11: QW | E11: =C11*Assumptions!B3 -> 63 | F11: 0.01 | G11: =F11*Assumptions!B9 -> 90 | H11: =G11*(1-Assumptions!B4)*Assumptions!B12 -> 458.629 | I11: =H11-E11 -> 395.629 | J11: =IF(C11>0,I11/C11,0) -> 131.87633 | K11: =IF(E11>0,H11/E11,0) -> 7.2798253 | L11: Funnels, churn, attribution analysis. Relevant to PSTN migration customer data.
A12: PHASE 4 | C12: INCREMENTAL — adds to Phases 1-3, does not dilute them
A13: PHASE 4 | B13: AI Engineer Career Path | C13: 40 | D13: 4 | E13: =C13*Assumptions!B3 -> 840 | F13: 1 | G13: =F13*Assumptions!B15 -> 2000 | H13: =G13*(1-Assumptions!B4)*Assumptions!B18 -> 9562.9471 | I13: =H13-E13 -> 8722.9471 | J13: =IF(C13>0,I13/C13,0) -> 218.07368 | K13: =IF(E13>0,H13/E13,0) -> 11.384461 | L13: LLM APIs, Streamlit apps, RAG, Hugging Face, deployment. Makes you someone who can BUILD with AI, not just understand it. Opens Commercial Director / AI transformation leadership roles.
A14: SKIP
A15: SKIP | B15: Intro to Generative AI | C15: <1 | D15: — | E15: — | F15: — | G15: — | H15: — | I15: — | J15: — | K15: — | L15: You already know all of this from daily use.
A16: SKIP | B16: Power BI / Tableau courses | C16: Var. | D16: — | E16: — | F16: — | G16: — | H16: — | I16: — | J16: — | K16: — | L16: Level 3 apprenticeship territory. YouTube tutorial material.
A17: SKIP | B17: Excel courses | C17: Var. | D17: — | E17: — | F17: — | G17: — | H17: — | I17: — | J17: — | K17: — | L17: You already build DCF models in Excel.
A18: SKIP | B18: Full career paths (50-90 hrs) | C18: 50-90 | D18: — | E18: — | F18: — | G18: — | H18: — | I18: — | J18: — | K18: — | L18: Too broad. Cherry-pick individual courses instead.
A20: SUMMARY BY TIER
B21: Courses | C21: Hrs | E21: Time Cost | F21: Weight | G21: Gross £/yr | H21: 5yr NPV | I21: Net Benefit | J21: Avg £/Hr | K21: Avg ROI
A22: TIER 1 | B22: 3 courses | C22: =SUM(C2:C4) -> 47 | E22: =SUM(E2:E4) -> 987 | F22: =SUM(F2:F4) -> 0.43 | G22: =SUM(G2:G4) -> 3870 | H22: =SUM(H2:H4) -> 19721.047 | I22: =SUM(I2:I4) -> 18734.047 | J22: =IF(C22>0,I22/C22,0) -> 398.59674 | K22: =IF(E22>0,H22/E22,0) -> 19.980797 | L22: Foundation courses — essential enablers
A23: TIER 2 | B23: 3 courses | C23: =SUM(C5:C7) -> 65 | E23: =SUM(E5:E7) -> 1365 | F23: =SUM(F5:F7) -> 0.52 | G23: =SUM(G5:G7) -> 4680 | H23: =SUM(H5:H7) -> 23848.708 | I23: =SUM(I5:I7) -> 22483.708 | J23: =IF(C23>0,I23/C23,0) -> 345.9032 | K23: =IF(E23>0,H23/E23,0) -> 17.471581 | L23: Strongest differentiators at senior level
A24: TIER 3 | B24: 4 courses | C24: =SUM(C8:C11) -> 11 | E24: =SUM(E8:E11) -> 231 | F24: =SUM(F8:F11) -> 0.05 | G24: =SUM(G8:G11) -> 450 | H24: =SUM(H8:H11) -> 2293.145 | I24: =SUM(I8:I11) -> 2062.145 | J24: =IF(C24>0,I24/C24,0) -> 187.46773 | K24: =IF(E24>0,H24/E24,0) -> 9.9270345 | L24: Quick wins and niche capabilities
A25: PHASE 4 | B25: 1 course (incremental) | C25: =C13 -> 40 | E25: =E13 -> 840 | F25: =F13 -> 1 | G25: =G13 -> 2000 | H25: =H13 -> 9562.9471 | I25: =I13 -> 8722.9471 | J25: =IF(C25>0,I25/C25,0) -> 218.07368 | K25: =IF(E25>0,H25/E25,0) -> 11.384461 | L25: Incremental — raises salary ceiling or accelerates arrival
A27: GRAND TOTAL | B27: 11 courses | C27: =SUM(C22:C25) -> 163 | E27: =SUM(E22:E25) -> 3423 | G27: =SUM(G22:G25) -> 11000 | H27: =SUM(H22:H25) -> 55425.847 | I27: =SUM(I22:I25) -> 52002.847 | J27: =IF(C27>0,I27/C27,0) -> 319.03587 | K27: =IF(E27>0,H27/E27,0) -> 16.192184 | L27: Complete recommended stack including AI Engineer

Sheet Sensitivity
A1: SCENARIO ANALYSIS
A2: Combined Net Benefit (all phases) under different assumptions
A3: Full career horizon (20 working years remaining)
A5: Total Uplift* \ Discount Rate | B5: 0.04 | C5: 0.05 | D5: 0.07 | E5: 0.09 | F5: 0.12
A6: £7,300 | B6: 45624 | C6: 40999 | D6: 33368 | E6: 27416 | F6: 20733
A7: £8,500 | B7: 53692 | C7: 48307 | D7: 39420 | E7: 32489 | F7: 24707
A8: £9,800 | B8: 62399 | C8: 56193 | D8: 45951 | E8: 37962 | F8: 28992
A9: £11,000 | B9: 70467 | C9: 63500 | D9: 52003 | E9: 43035 | F9: 32967
A10: £12,200 | B10: 78535 | C10: 70807 | D10: 58055 | E10: 48108 | F10: 36941
A12: * Combined Phase 1-3 + Phase 4 uplift
A13: Highlighted = base case (£9k + £2k, 7% discount)
A14: All scenarios: 42% tax, 163 total hours at £21/hr (net take-home), 20yr working horizon
A16: BREAKEVEN ANALYSIS
A17: Min combined annual uplift to break even: | B17: 680 | C17: per year gross (at 7%, 42% tax, career horizon)
A18: Your target range: | B18: £8,000-£12,200 | C18: 4-7x above breakeven in all scenarios
