Workbook

Sheet Course Analysis
A1: Tier | B1: Course | C1: Hours | D1: Time Cost | E1: Uplift Share | F1: Gross Uplift £/yr | G1: 5yr NPV (post-tax) | H1: Net Benefit | I1: Benefit/Hour | J1: ROI Multiple | K1: Rationale
A2: TIER 1 | B2: Learn Python 3 | C2: 24 | D2: =C2*Assumptions!B5 -> 888 | E2: 0.25 | F2: =E2*Assumptions!B1 -> 2250 | G2: =F2*(1-Assumptions!B3)*Assumptions!B7 -> 5000.7081 | H2: =G2-D2 -> 4112.7081 | I2: =IF(C2>0,H2/C2,0) -> 171.36284 | J2: =IF(D2>0,G2/D2,0) -> 5.631428 | K2: Foundation for everything else. Enables automation, financial modelling, AI tooling, and Data Fellowship prep.
A3: TIER 1 | B3: Learn SQL | C3: 5 | D3: =C3*Assumptions!B5 -> 185 | E3: 0.08 | F3: =E3*Assumptions!B1 -> 720 | G3: =F3*(1-Assumptions!B3)*Assumptions!B7 -> 1600.2266 | H3: =G3-D3 -> 1415.2266 | I3: =IF(C3>0,H3/C3,0) -> 283.04532 | J3: =IF(D3>0,G3/D3,0) -> 8.6498734 | K3: Table stakes at senior analytical level. Query pricing databases directly without waiting for data team.
A4: TIER 1 | B4: Analyze Data with SQL (Skill Path) | C4: 18 | D4: =C4*Assumptions!B5 -> 666 | E4: 0.1 | F4: =E4*Assumptions!B1 -> 900 | G4: =F4*(1-Assumptions!B3)*Assumptions!B7 -> 2000.2832 | H4: =G4-D4 -> 1334.2832 | I4: =IF(C4>0,H4/C4,0) -> 74.126846 | J4: =IF(D4>0,G4/D4,0) -> 3.0034283 | K4: Takes SQL from basic to practical. Joins, aggregates, real case studies on Ethernet/Optical pricing data.
A5: TIER 2 | B5: Analyze Financial Data with Python (Skill Path) | C5: 20 | D5: =C5*Assumptions!B5 -> 740 | E5: 0.2 | F5: =E5*Assumptions!B1 -> 1800 | G5: =F5*(1-Assumptions!B3)*Assumptions!B7 -> 4000.5665 | H5: =G5-D5 -> 3260.5665 | I5: =IF(C5>0,H5/C5,0) -> 163.02832 | J5: =IF(D5>0,G5/D5,0) -> 5.4061709 | K5: Pandas, NumPy, Matplotlib, regression, portfolio optimisation. Maps directly to pricing models and personal investments.
A6: TIER 2 | B6: Learn Statistics with Python | C6: 10 | D6: =C6*Assumptions!B5 -> 370 | E6: 0.1 | F6: =E6*Assumptions!B1 -> 900 | G6: =F6*(1-Assumptions!B3)*Assumptions!B7 -> 2000.2832 | H6: =G6-D6 -> 1630.2832 | I6: =IF(C6>0,H6/C6,0) -> 163.02832 | J6: =IF(D6>0,G6/D6,0) -> 5.4061709 | K6: Distributions, variance, hypothesis testing. Essential foundation before ML content makes sense.
A7: TIER 2 | B7: ML/AI Engineer Career Path (first 60-70%) | C7: 35 | D7: =C7*Assumptions!B5 -> 1295 | E7: 0.22 | F7: =E7*Assumptions!B1 -> 1980 | G7: =F7*(1-Assumptions!B3)*Assumptions!B7 -> 4400.6231 | H7: =G7-D7 -> 3105.6231 | I7: =IF(C7>0,H7/C7,0) -> 88.732089 | J7: =IF(D7>0,G7/D7,0) -> 3.3981646 | K7: Commercial leaders with ML literacy are rare. Strongest differentiator for Head of Pricing / Commercial Director.
A8: TIER 3 | B8: Learn How to Use AI for Data Analysis | C8: 3 | D8: =C8*Assumptions!B5 -> 111 | E8: 0.02 | F8: =E8*Assumptions!B1 -> 180 | G8: =F8*(1-Assumptions!B3)*Assumptions!B7 -> 400.05665 | H8: =G8-D8 -> 289.05665 | I8: =IF(C8>0,H8/C8,0) -> 96.352216 | J8: =IF(D8>0,G8/D8,0) -> 3.6041139 | K8: Using LLMs as analytics assistants in Python. Productivity tool, minimal standalone salary impact.
A9: TIER 3 | B9: Web Scraping with Beautiful Soup | C9: 4 | D9: =C9*Assumptions!B5 -> 148 | E9: 0.01 | F9: =E9*Assumptions!B1 -> 90 | G9: =F9*(1-Assumptions!B3)*Assumptions!B7 -> 200.02832 | H9: =G9-D9 -> 52.028324 | I9: =IF(C9>0,H9/C9,0) -> 13.007081 | J9: =IF(D9>0,G9/D9,0) -> 1.3515427 | K9: Pull competitor pricing, Ofcom data programmatically. Niche but defensible competitive intelligence capability.
A10: TIER 3 | B10: AI for FP&A | C10: 1 | D10: =C10*Assumptions!B5 -> 37 | E10: 0.01 | F10: =E10*Assumptions!B1 -> 90 | G10: =F10*(1-Assumptions!B3)*Assumptions!B7 -> 200.02832 | H10: =G10-D10 -> 163.02832 | I10: =IF(C10>0,H10/C10,0) -> 163.02832 | J10: =IF(D10>0,G10/D10,0) -> 5.4061709 | K10: Forecasting, scenario modelling, variance analysis with AI. Directly relevant but too narrow to move salary needle alone.
A11: TIER 3 | B11: SQL for Business Metrics (Intermediate) | C11: 3 | D11: =C11*Assumptions!B5 -> 111 | E11: 0.01 | F11: =E11*Assumptions!B1 -> 90 | G11: =F11*(1-Assumptions!B3)*Assumptions!B7 -> 200.02832 | H11: =G11-D11 -> 89.028324 | I11: =IF(C11>0,H11/C11,0) -> 29.676108 | J11: =IF(D11>0,G11/D11,0) -> 1.802057 | K11: Funnels, churn, attribution analysis. Relevant to PSTN migration customer behaviour data.
A12: SKIP | B12: Intro to Generative AI | C12: <1 | D12: — | E12: — | F12: — | G12: — | H12: — | I12: — | J12: — | K12: You already know all of this from daily use.
A13: SKIP | B13: Power BI / Tableau courses | C13: Var. | D13: — | E13: — | F13: — | G13: — | H13: — | I13: — | J13: — | K13: Level 3 apprenticeship territory. YouTube tutorial material.
A14: SKIP | B14: Excel courses | C14: Var. | D14: — | E14: — | F14: — | G14: — | H14: — | I14: — | J14: — | K14: You already build DCF models in Excel.
A15: SKIP | B15: Full career paths (50-90 hrs) | C15: 50-90 | D15: — | E15: — | F15: — | G15: — | H15: — | I15: — | J15: — | K15: Too broad. Cherry-pick individual courses instead.
A17: TIER SUMMARY
B18: Courses | C18: Hours | D18: Time Cost | E18: Weight | F18: Gross Uplift | G18: 5yr NPV | H18: Net Benefit | I18: Avg Benefit/Hr | J18: Avg ROI
A19: TIER 1 | B19: 3 courses | C19: =SUM(C2:C4) -> 47 | D19: =SUM(D2:D4) -> 1739 | E19: =SUM(E2:E4) -> 0.43 | F19: =SUM(F2:F4) -> 3870 | G19: =SUM(G2:G4) -> 8601.2179 | H19: =SUM(H2:H4) -> 6862.2179 | I19: =IF(C19>0,H19/C19,0) -> 146.00464 | J19: =IF(D19>0,G19/D19,0) -> 4.9460713 | K19: Foundation courses - essential enablers
A20: TIER 2 | B20: 3 courses | C20: =SUM(C5:C7) -> 65 | D20: =SUM(D5:D7) -> 2405 | E20: =SUM(E5:E7) -> 0.52 | F20: =SUM(F5:F7) -> 4680 | G20: =SUM(G5:G7) -> 10401.473 | H20: =SUM(H5:H7) -> 7996.4728 | I20: =IF(C20>0,H20/C20,0) -> 123.02266 | J20: =IF(D20>0,G20/D20,0) -> 4.3249367 | K20: Strongest differentiators at senior level
A21: TIER 3 | B21: 4 courses | C21: =SUM(C8:C11) -> 11 | D21: =SUM(D8:D11) -> 407 | E21: =SUM(E8:E11) -> 0.05 | F21: =SUM(F8:F11) -> 450 | G21: =SUM(G8:G11) -> 1000.1416 | H21: =SUM(H8:H11) -> 593.14162 | I21: =IF(C21>0,H21/C21,0) -> 53.921965 | J21: =IF(D21>0,G21/D21,0) -> 2.4573504 | K21: Quick wins and niche capabilities
A23: TOTAL | B23: 10 courses | C23: =SUM(C19:C21) -> 123 | D23: =SUM(D19:D21) -> 4551 | E23: =SUM(E19:E21) -> 1 | F23: =SUM(F19:F21) -> 9000 | G23: =SUM(G19:G21) -> 20002.832 | H23: =SUM(H19:H21) -> 15451.832 | I23: =IF(C23>0,H23/C23,0) -> 125.62465 | J23: =IF(D23>0,G23/D23,0) -> 4.3952609 | K23: Complete recommended skillset stack

Sheet Assumptions
A1: Total Annual Salary Uplift Target | B1: 9000 | C1: Midpoint-high of £6-10k range. Adjust to test scenarios.
A2: Current Salary | B2: 72000 | C2: For reference only - not used in calculations.
A3: Combined Tax/NI Rate | B3: 0.42 | C3: Marginal rate at £72k+. 40% income tax + 2% NI.
A4: Discount Rate | B4: 0.07 | C4: Time value of money. 7% = equity-like opportunity cost.
A5: Hourly Time Value | B5: 37 | C5: Based on salary + ~30% employer costs, divided by working hours.
A6: Delay Before Uplift (years) | B6: 1 | C6: Years before salary uplift kicks in. 1 = conservative (full stack built first).
A7: Delayed Annuity Factor (5yr) | B7: =(1/(1+B4)^(B6+1) + 1/(1+B4)^(B6+2) + 1/(1+B4)^(B6+3) + 1/(1+B4)^(B6+4) + 1/(1+B4)^(B6+5)) -> 3.8319602 | C7: Sum of discount factors for years (delay+1) to (delay+5). Derived from inputs above.
A8: NPV Horizon (years of uplift) | B8: 5 | C8: Years of salary uplift after delay period. Hardcoded into annuity factor formula.
A10: METHODOLOGY
A11: Each course is assigned a contribution weight (% of total salary uplift it enables).
A12: Weights sum to 100% across all 10 recommended courses - no double-counting.
A13: Courses are interdependent (Python enables Financial Python enables ML).
A14: The weight reflects marginal contribution within the integrated stack.
A15: NPV = Gross Uplift * (1 - Tax Rate) * Delayed Annuity Factor.
A16: Net Benefit = NPV - Time Cost. Positive = course pays back more than time invested.
A17: Benefit/Hour = Net Benefit / Hours. Higher = more efficient use of your time.
A18: ROI Multiple = NPV / Time Cost. >1.0x means positive return.
A19: Blue cells are adjustable inputs. Black cells are formulas. Change blue to run scenarios.
A21: KEY DIFFERENCE FROM ALTERNATIVE MODEL
A22: The alternative model used independent salary estimates per course summing to £10,700/yr.
... A26: Result: lower but more defensible NPV figures. Every positive Net Benefit is genuinely earned.

Sheet Sensitivity
A1: SCENARIO ANALYSIS
A2: Total Net Benefit under different assumptions
A4: Total Uplift \ Discount Rate | B4: 0.04 | C4: 0.05 | D4: 0.07 | E4: 0.09 | F4: 0.12
A5: 6000 | B5: 10345 | C5: 9798 | D5: 8784 | E5: 7867 | F5: 6650
A6: 7000 | B6: 12828 | C6: 12190 | D6: 11007 | E6: 9937 | F6: 8516
A7: 8000 | B7: 15311 | C7: 14581 | D7: 13229 | E7: 12007 | F7: 10383
A8: 9000 | B8: 17794 | C8: 16973 | D8: 15452 | E8: 14077 | F8: 12250
A9: 10000 | B9: 20276 | C9: 19364 | D9: 17674 | E9: 16146 | F9: 14117
A11: Highlighted cell = base case assumptions
A12: All scenarios assume 42% tax, 1-year delay, 123 total hours at £37/hr
A13: Green = positive net benefit. Red = time cost exceeds NPV.
A15: BREAKEVEN ANALYSIS
A16: Minimum annual uplift to break even: | B16: 2048 | C16: per year gross (at base case 7% discount, 42% tax, 1yr delay)
A17: Your target range: | B17: £6,000-£10,000 | C17: Comfortably above breakeven in all scenarios
